<?xml version="1.0"?>
<!DOCTYPE hibernate-mapping PUBLIC "-//Hibernate/Hibernate Mapping DTD 3.0//EN"
"http://hibernate.sourceforge.net/hibernate-mapping-3.0.dtd">
<!-- Generated by T-Systems -->
<hibernate-mapping>
    <class name="com.rsi.agp.dao.tables.comisiones.recibosEmitidos.ReciboEmitidoAplicacion" table="TB_COMS_RECS_EMITIDOS_APLI">
        <id name="id" type="java.lang.Long">
            <column name="ID" precision="15" scale="0" />
            <generator class="sequence">
            	<param name="sequence">SQ_COMS_RECS_EMITIDOS_APLI</param>
            </generator>
        </id>
        <many-to-one name="reciboEmitido" class="com.rsi.agp.dao.tables.comisiones.recibosEmitidos.ReciboEmitido" fetch="select">
            <column name="IDRECIBOEMITIDO" precision="15" scale="0" not-null="true" />
        </many-to-one>
        <property name="referencia" type="string">
            <column name="REFERENCIA" length="7" />
        </property>
        <property name="digitocontrol" type="java.math.BigDecimal">
            <column name="DIGITOCONTROL" precision="1" scale="0" />
        </property>
        <property name="nifcif" type="string">
            <column name="NIFCIF" length="9" />
        </property>
        <property name="tiporeferencia" type="java.lang.Character">
            <column name="TIPOREFERENCIA" length="1" />
        </property>
        <property name="tiporecibo" type="java.lang.Character">
            <column name="TIPORECIBO" length="1" />
        </property>
        <property name="nombre" type="string">
            <column name="NOMBRE" length="20" />
        </property>
        <property name="apellido1" type="string">
            <column name="APELLIDO1" length="40" />
        </property>
        <property name="apellido2" type="string">
            <column name="APELLIDO2" length="40" />
        </property>
        <property name="razonsocial" type="string">
            <column name="RAZONSOCIAL" length="100" />
        </property>
        <property name="saldopoliza" type="java.math.BigDecimal">
            <column name="SALDOPOLIZA" precision="13" />
        </property>
        <property name="primacomercial" type="java.math.BigDecimal">
            <column name="PRIMACOMERCIAL" precision="13" />
        </property>
        <property name="bonsistproteccion" type="java.math.BigDecimal">
            <column name="BONSISTPROTECCION" precision="13" />
        </property>
        <property name="bonificacion" type="java.math.BigDecimal">
            <column name="BONIFICACION" precision="13" />
        </property>
        <property name="recargo" type="java.math.BigDecimal">
            <column name="RECARGO" precision="13" />
        </property>
        <property name="dtocolectivo" type="java.math.BigDecimal">
            <column name="DTOCOLECTIVO" precision="13" />
        </property>
        <property name="dtoventanilla" type="java.math.BigDecimal">
            <column name="DTOVENTANILLA" precision="13" />
        </property>
        <property name="primaneta" type="java.math.BigDecimal">
            <column name="PRIMANETA" precision="13" />
        </property>
        <property name="consorcio" type="java.math.BigDecimal">
            <column name="CONSORCIO" precision="13" />
        </property>
        <property name="clea" type="java.math.BigDecimal">
            <column name="CLEA" precision="13" />
        </property>
        <property name="costeneto" type="java.math.BigDecimal">
            <column name="COSTENETO" precision="13" />
        </property>
        <property name="subenesa" type="java.math.BigDecimal">
            <column name="SUBENESA" precision="13" />
        </property>
        <property name="costetomador" type="java.math.BigDecimal">
            <column name="COSTETOMADOR" precision="13" />
        </property>
        <property name="pagos" type="java.math.BigDecimal">
            <column name="PAGOS" precision="13" />
        </property>
        <property name="de1PrimaComercial" type="java.math.BigDecimal">
            <column name="DE1_PRIMA_COMERCIAL" precision="13" />
        </property>
        <property name="de1PrimaComercialNeta" type="java.math.BigDecimal">
            <column name="DE1_PRIMA_COMERCIAL_NETA" precision="13" />
        </property>
        <property name="de1RecargoConsorcio" type="java.math.BigDecimal">
            <column name="DE1_RECARGO_CONSORCIO" precision="13" />
        </property>
        <property name="de1ReciboPrima" type="java.math.BigDecimal">
            <column name="DE1_RECIBO_PRIMA" precision="13" />
        </property>
        <property name="de1SubvEnesa" type="java.math.BigDecimal">
            <column name="DE1_SUBV_ENESA" precision="13" />
        </property>
        <property name="de1CosteTomador" type="java.math.BigDecimal">
            <column name="DE1_COSTE_TOMADOR" precision="13" />
        </property>
        <property name="de1TotalCosteTomador" type="java.math.BigDecimal">
            <column name="DE1_TOTAL_COSTE_TOMADOR" precision="13" />
        </property>
        <property name="de1Pagos" type="java.math.BigDecimal">
            <column name="DE1_PAGOS" precision="13" />
        </property>
        <property name="de1Diferencia" type="java.math.BigDecimal">
            <column name="DE1_DIFERENCIA" precision="13" />
        </property>
        <property name="de1RecargoAval" type="java.math.BigDecimal">
            <column name="DE1_RECARGO_AVAL" precision="13" />
        </property>
        <property name="de1RecargoFracc" type="java.math.BigDecimal">
            <column name="DE1_RECARGO_FRACC" precision="13" />
        </property>
        <property name="domiciliado" type="java.lang.Character">
            <column name="DOMICILIADO" length="1" />
        </property>
        <property name="destDomiciliacion" type="java.lang.Character">
            <column name="DEST_DOMICILIACION" length="1" />
        </property>
        <property name="de1ImpDomiciliado" type="java.math.BigDecimal">
            <column name="DE1_IMP_DOMICILIADO" precision="13" />
        </property>
        <set name="reciboEmitidoApliSubvCCAAs" table="TB_COMS_RECS_EMI_APLI_CCAA" inverse="true" lazy="true" fetch="select" cascade="all">
            <key>
                <column name="IDAPLI" precision="15" scale="0" not-null="true" />
            </key>
            <one-to-many class="com.rsi.agp.dao.tables.comisiones.recibosEmitidos.ReciboEmitidoApliSubvCCAA" />
        </set>
        <set name="reciboEmitidoApliBonRecs" table="TB_COMS_RECS_EMI_APLI_BON_REC" inverse="true" lazy="true" fetch="select" cascade="all">
            <key>
                <column name="IDAPLI" precision="15" scale="0" not-null="true">
                    <comment>Identificador que referencia a la tabla TB_COMS_RECS_EMITIDOS_APLI</comment>
                </column>
            </key>
            <one-to-many class="com.rsi.agp.dao.tables.comisiones.recibosEmitidos.ReciboEmitidoApliBonRec" />
        </set>
    </class>
</hibernate-mapping>
