<?xml version="1.0"?>
<!DOCTYPE hibernate-mapping PUBLIC "-//Hibernate/Hibernate Mapping DTD 3.0//EN"
"http://hibernate.sourceforge.net/hibernate-mapping-3.0.dtd">
<!-- Generated by T-Systems -->
<hibernate-mapping>
    <class name="com.rsi.agp.dao.tables.cgen.Organismo" table="TB_SC_C_ORGANISMOS">
        <comment>Organismos</comment>
        <id name="codorganismo" type="java.lang.Character">
            <column name="CODORGANISMO" length="1" />
            <generator class="assigned" />
        </id>
        <property name="desorganismo" type="string">
            <column name="DESORGANISMO" length="30" not-null="true">
                <comment>Descripcisn del organismo.</comment>
            </column>
        </property>
        <set name="provincias" table="TB_SC_C_PROVS_ORGANISMO" inverse="false" lazy="true" fetch="select">
            <key>
                <column name="CODORGANISMO" length="1" not-null="true">
                    <comment>Organismo</comment>
                </column>
            </key>
            <many-to-many entity-name="com.rsi.agp.dao.tables.commons.Provincia">
                <column name="CODPROVINCIA" precision="2" scale="0" not-null="true">
                    <comment>Provincia</comment>
                </column>
            </many-to-many>
        </set>
        <set name="subvencionCCAAs" table="TB_SC_C_SUBVS_CCAA" inverse="true" lazy="true" fetch="select">
            <key>
                <column name="CODORGANISMO" length="1" not-null="true">
                    <comment>Organismo</comment>
                </column>
            </key>
            <one-to-many class="com.rsi.agp.dao.tables.cpl.SubvencionCCAA" />
        </set>
        <set name="sistemaReduccionSubvCCAAs" table="TB_SC_C_SIST_REDUC_SUBV_CCAA" inverse="true" lazy="true" fetch="select">
            <key>
                <column name="CODORGANISMO" length="1" not-null="true">
                    <comment>Organismo</comment>
                </column>
            </key>
            <one-to-many class="com.rsi.agp.dao.tables.cpl.SistemaReduccionSubvCCAA" />
        </set>
        <set name="tiposSubvIncompCalculadases" table="TB_SC_C_SUBV_INCOMP_CAL" inverse="true" lazy="true" fetch="select">
            <key>
                <column name="CODORGANISMO" length="1" not-null="true">
                    <comment>Organismo</comment>
                </column>
            </key>
            <one-to-many class="com.rsi.agp.dao.tables.cpl.TiposSubvIncompCalculadas" />
        </set>
        <set name="aseguradoNoSubvencionables" table="TB_SC_C_ASEG_NO_SUBVENCIONABLE" inverse="true" lazy="true" fetch="select">
            <key>
                <column name="CODORGANISMO" length="1" not-null="true">
                    <comment>Csdigo del organismo</comment>
                </column>
            </key>
            <one-to-many class="com.rsi.agp.dao.tables.cgen.AseguradoNoSubvencionable" />
        </set>
    </class>
</hibernate-mapping>
