<?xml version="1.0"?>
<!DOCTYPE hibernate-mapping PUBLIC "-//Hibernate/Hibernate Mapping DTD 3.0//EN"
"http://hibernate.sourceforge.net/hibernate-mapping-3.0.dtd">
<!-- Generated by T-Systems -->
<hibernate-mapping>
    <class name="com.rsi.agp.dao.tables.rc.RegimenRC" table="TB_RC_REGIMEN">
        <comment>Registros de r&#233;gimen para el c&#225;lculo de la RC de Ganado</comment>
        <id name="codregimen" type="java.math.BigDecimal">
            <column name="CODREGIMEN" precision="2" scale="0" />
            <generator class="assigned" />
        </id>
        <property name="descripcion" type="string">
            <column name="DESCRIPCION" length="50" not-null="true">
                <comment>Descripci&#243;n del registro de r&#233;gimen</comment>
            </column>
        </property>
        <set name="datosRCs" table="TB_RC_DATOS" inverse="true" lazy="true" fetch="select">
            <key>
                <column name="CODREGIMEN_RC" precision="2" scale="0" not-null="true">
                    <comment>C&#243;digo de r&#233;gimen de RC</comment>
                </column>
            </key>
            <one-to-many class="com.rsi.agp.dao.tables.rc.DatosRC" />
        </set>
        <set name="polizasRCs" table="TB_RC_POLIZAS" inverse="true" lazy="true" fetch="select">
            <key>
                <column name="CODREGIMEN_RC" precision="2" scale="0" not-null="true" />
            </key>
            <one-to-many class="com.rsi.agp.dao.tables.rc.PolizasRC" />
        </set>
    </class>
</hibernate-mapping>
