<?xml version="1.0"?>
<!DOCTYPE hibernate-mapping PUBLIC "-//Hibernate/Hibernate Mapping DTD 3.0//EN"
"http://hibernate.sourceforge.net/hibernate-mapping-3.0.dtd">
<!-- Generated by T-Systems -->
<hibernate-mapping>
    <class name="com.rsi.agp.dao.tables.recibos.ReciboDetCompensacion" table="TB_RECIBO_DET_COMPENSACION">
        <comment>DETALLES COMPENSACION RECIBO</comment>
        <id name="id" type="long">
            <column name="ID" precision="15" scale="0" />
						<generator class="sequence">
            	<param name="sequence">SQ_TB_RECIBO_DET_COMPENSACION</param>
            </generator>        
        </id>
        <many-to-one name="recibo" class="com.rsi.agp.dao.tables.recibos.Recibo" fetch="select">
            <column name="IDRECIBO" precision="15" scale="0" not-null="true">
                <comment>Identificador del Recibo</comment>
            </column>
        </many-to-one>
        <property name="plandeudor" type="java.math.BigDecimal">
            <column name="PLANDEUDOR" precision="4" scale="0">
                <comment>Plan Deudor</comment>
            </column>
        </property>
        <property name="lineadeudor" type="java.math.BigDecimal">
            <column name="LINEADEUDOR" precision="3" scale="0">
                <comment>Linea Deudor</comment>
            </column>
        </property>
        <property name="numrecibodeudor" type="java.math.BigDecimal">
            <column name="NUMRECIBODEUDOR" precision="6" scale="0">
                <comment>Numero Recibo Deudor</comment>
            </column>
        </property>
        <property name="cobrodeudor" type="java.math.BigDecimal">
            <column name="COBRODEUDOR" precision="11">
                <comment>Cobro Deudor</comment>
            </column>
        </property>
    </class>
</hibernate-mapping>
