<?xml version="1.0"?>
<!DOCTYPE hibernate-mapping PUBLIC "-//Hibernate/Hibernate Mapping DTD 3.0//EN"
"http://hibernate.sourceforge.net/hibernate-mapping-3.0.dtd">
<!-- Generated by T-Systems -->
<hibernate-mapping>
    <class name="com.rsi.agp.dao.tables.commons.Oficina" table="TB_OFICINAS">
        <comment>Oficinas</comment>
        <composite-id name="id" class="com.rsi.agp.dao.tables.commons.OficinaId">
            <key-property name="codentidad" type="java.math.BigDecimal">
                <column name="CODENTIDAD" precision="4" scale="0" />
            </key-property>
            <key-property name="codoficina" type="java.math.BigDecimal">
                <column name="CODOFICINA" precision="4" scale="0" />
            </key-property>
        </composite-id>
        <many-to-one name="entidad" class="com.rsi.agp.dao.tables.admin.Entidad" lazy="no-proxy" update="false" insert="false" fetch="select">
            <column name="CODENTIDAD" precision="4" scale="0" not-null="true">
                <comment>Entidad</comment>
            </column>
        </many-to-one>
        <property name="nomoficina" type="string">
            <column name="NOMOFICINA" length="40" not-null="true">
                <comment>Nombre de la oficina</comment>
            </column>
        </property>
        <property name="pagoManual" type="java.math.BigDecimal">
            <column name="PAGO_MANUAL" precision="1" scale="0" not-null="true">
                <comment>Indicador de pago manual para la oficina (0 - No, 1 - Si)</comment>
            </column>
        </property>
         <property name="idgrupo" type="java.math.BigDecimal">
            <column name="IDGRUPO" precision="3" scale="0" not-null="false">
                <comment>Id del grupo al que pertenece la oficina</comment>
            </column>
        </property>
        <set name="usuarios" table="TB_USUARIOS" inverse="true" lazy="extra" fetch="select">
            <key>
                <column name="CODENTIDAD" precision="4" scale="0">
                    <comment>Entidad</comment>
                </column>
                <column name="CODOFICINA" precision="4" scale="0">
                    <comment>Oficina</comment>
                </column>
            </key>
            <one-to-many class="com.rsi.agp.dao.tables.commons.Usuario" />
        </set>
        <set name="oficinasZona" table="TB_OFICINAS_ZONAS" inverse="true" lazy="extra" fetch="select">
            <key>
                <column name="CODENTIDAD" precision="4" scale="0">
                    <comment>Entidad</comment>
                </column>
                <column name="CODOFICINA" precision="4" scale="0">
                    <comment>Oficina</comment>
                </column>
            </key>
            <one-to-many class="com.rsi.agp.dao.tables.commons.OficinasZona" />
        </set>
       
    </class>
</hibernate-mapping>
