<?xml version="1.0"?>
<!DOCTYPE hibernate-mapping PUBLIC "-//Hibernate/Hibernate Mapping DTD 3.0//EN"
"http://hibernate.sourceforge.net/hibernate-mapping-3.0.dtd">
<!-- Generated by T-Systems -->
<hibernate-mapping>
    <class name="com.rsi.agp.dao.tables.cesp.PeriodoGarantiaCe" table="TB_PERIODOS_GARANTIAS_CE">
        <comment>Periodos de garant&#237;as de Condiciones Especiales</comment>
        <id name="id" type="java.math.BigDecimal">
            <column name="ID" precision="15" scale="0" />
            <generator class="assigned" />
        </id>
        <many-to-one name="modulo" class="com.rsi.agp.dao.tables.cpl.Modulo" fetch="select">
            <column name="LINEASEGUROID" precision="15" scale="0" not-null="true">
                <comment>Identificador de la l&#237;nea</comment>
            </column>
            <column name="CODMODULO" length="5" not-null="true">
                <comment>M&#243;dulo</comment>
            </column>
        </many-to-one>
        <many-to-one name="conceptoPpalModulo" class="com.rsi.agp.dao.tables.cgen.ConceptoPpalModulo" fetch="select" lazy="no-proxy">
            <column name="CODCONCEPTOPPALMOD" precision="3" scale="0" not-null="true">
                <comment>Concepto principal del m&#243;dulo</comment>
            </column>
        </many-to-one>
        <many-to-one name="cultivo" class="com.rsi.agp.dao.tables.cpl.Cultivo" update="false" insert="false" fetch="select" lazy="no-proxy">
            <column name="LINEASEGUROID" precision="15" scale="0" not-null="true">
                <comment>Identificador de la l&#237;nea</comment>
            </column>
            <column name="CODCULTIVO" precision="3" scale="0" not-null="true">
                <comment>Cultivo</comment>
            </column>
        </many-to-one>
        <many-to-one name="linea" class="com.rsi.agp.dao.tables.poliza.Linea" update="false" insert="false" fetch="select" lazy="no-proxy">
            <column name="LINEASEGUROID" precision="15" scale="0" not-null="true">
                <comment>Identificador de la l&#237;nea</comment>
            </column>
        </many-to-one>
        <property name="codriesgocubierto" type="java.math.BigDecimal">
            <column name="CODRIESGOCUBIERTO" precision="3" scale="0" not-null="true">
                <comment>Riesgo cubierto</comment>
            </column>
        </property>
        <property name="fechaini" type="date">
            <column name="FECHAINI" length="7">
                <comment>Fecha de inicio de la garant&#237;a</comment>
            </column>
        </property>
        <property name="fechafin" type="date">
            <column name="FECHAFIN" length="7">
                <comment>Fecha de fin de la garant&#237;a</comment>
            </column>
        </property>
        <property name="estadofenologicoini" type="java.lang.Character">
            <column name="ESTADOFENOLOGICOINI" length="1">
                <comment>Estado fenol&#243;gico inicial</comment>
            </column>
        </property>
        <property name="estadofenologicofin" type="java.lang.Character">
            <column name="ESTADOFENOLOGICOFIN" length="1">
                <comment>Estado fenol&#243;gico final</comment>
            </column>
        </property>
        <property name="nummesesini" type="java.math.BigDecimal">
            <column name="NUMMESESINI" precision="3" scale="0">
                <comment>N&#250;mero de meses inicial</comment>
            </column>
        </property>
        <property name="nummesesfin" type="java.math.BigDecimal">
            <column name="NUMMESESFIN" precision="3" scale="0">
                <comment>N&#250;mero de meses final</comment>
            </column>
        </property>
        <property name="numdiasini" type="java.math.BigDecimal">
            <column name="NUMDIASINI" precision="2" scale="0">
                <comment>N&#250;mero de dias inicial.</comment>
            </column>
        </property>
        <property name="numdiasfin" type="java.math.BigDecimal">
            <column name="NUMDIASFIN" precision="2" scale="0">
                <comment>N&#250;mero de d&#237;as final</comment>
            </column>
        </property>
        <property name="codvariedad" type="java.math.BigDecimal">
            <column name="CODVARIEDAD" precision="3" scale="0">
                <comment>Codigo variedad</comment>
            </column>
        </property>
    </class>
</hibernate-mapping>
